Metadata-Version: 1.0
Name: czyutils
Version: 1.1
Summary: 测试组件包
Home-page: https://www.cnblogs.com/RainBol/
Author: RainBol
Author-email: 2497643794@qq.com
License: UNKNOWN
Platform: UNKNOWN
